{"schema_version":1,"events":[{"id":"evt.eir.clinic_triage","legacy_id":"EVT-EIR-01","title_en":"Clinic Triage","location_id":"loc.eientei","lead_character_ids":["char.eirin_yagokoro"],"primary_mode":"triage_minigame","core_change":"Eirin separates observed signs, patient statements, magical residue, and Tewi's rumor cards before any treatment decision can overwrite the person being assessed.","status":"implemented","estimated_minutes":15,"comfort_tags":["no_timer","assist_available","loss_continues","medical_consent","no_real_world_treatment_advice"]}]}
