{"schema":"gmh-deferred-references-v1","references":[{"id":"loc.forest_of_magic.forest_edge","kind":"spot","target_milestone":"M14","reason":"Crash Landing begins at the Forest of Magic edge."},{"id":"prop.marisa_cargo","kind":"interactable","target_milestone":"M14","reason":"Borrowed books and a returned object are visible cargo."},{"id":"prop.marisa_broom","kind":"interactable","target_milestone":"M14","reason":"The broom anchors the Backseat tutorial."},{"id":"mini.mrs.broom_backseat","kind":"minigame","target_milestone":"M14","reason":"Deterministic cargo-balance tutorial for Marisa's route."},{"id":"journal.mrs.crash_landing","kind":"journal_entry","target_milestone":"M14","reason":"The opening route observation records responsibility before romance."}]}
