{"schema":"gmh-deferred-references-v1","references":[{"id":"loc.heaven.unwitnessed_boundary_repair","kind":"spot","target_milestone":"M14","reason":"The repaired boundary is first visible without Tenshi present, protecting the condition that repair was not performed for an audience."},{"id":"prop.tsh.visible_repair_seam","kind":"interactable","target_milestone":"M14","reason":"A bold pale seam across black stone makes repair legible without pretending the crossing never occurred."},{"id":"prop.tsh.unclaimed_tool_tray","kind":"interactable","target_milestone":"M14","reason":"An empty unmarked tray shows work happened while refusing trophy or credit imagery."},{"id":"prop.tsh.reopened_delivery_path","kind":"interactable","target_milestone":"M14","reason":"The cart route visibly reopened before Tenshi arrives provides independent evidence of repair."},{"id":"journal.tsh.repair_she_finishes","kind":"journal_entry","target_milestone":"M14","reason":"The journal records unwitnessed repair, no credit demand, a visible seam, and strain repaired only through practice."}]}
